Workbook
Name aporte: Planilha1!$D$15
Name patrimonio: Planilha1!$D$18
Name qtd_anos: Planilha1!$D$16
Name rendimento_carteira: Planilha1!$D$11
Name salario: Planilha1!$D$10
Name sugestao_investimento: Planilha1!$D$12
Name taxa_mensal: Planilha1!$D$17

Sheet Planilha1
B9: CONFIGURAÇÕES
B10: Salário | D10: 5000
B11: Rendimento carteira | D11: 0.006
B12: Sugestão de investimento | D12: =D10*30% -> 1500
B14: INVESTIMENTO MENSAL
B15: Quanto investir por mês? | D15: 200
B16: Por quantos anos? | D16: 10
B17: Taxa de rendimento mensal? | D17: 0.01079
B18: Patrimônio acumulado? | D18: =FV(taxa_mensal,qtd_anos*12,aporte*-1) -> 48656.843
B19: Dividendos mensais? | D19: =patrimonio*rendimento_carteira -> 291.94106
B21: CENÁRIOS | D21: DIVIDENDO
A22: 2 | B22: Quanto em 2 anos? | C22: =FV($D$17,$A22*12,$D$15*-1) -> 5445.5255 | D22: =C22*rendimento_carteira -> 32.673153
A23: 5 | B23: Quanto em 5 anos? | C23: =FV($D$17,$A23*12,$D$15*-1) -> 16755.383 | D23: =C23*rendimento_carteira -> 100.5323
A24: 10 | B24: Quanto em 10 anos? | C24: =FV($D$17,$A24*12,$D$15*-1) -> 48656.843 | D24: =C24*rendimento_carteira -> 291.94106
A25: 20 | B25: Quanto em 20 anos? | C25: =FV($D$17,$A25*12,$D$15*-1) -> 225039.68 | D25: =C25*rendimento_carteira -> 1350.2381
A26: 30 | B26: Quanto em 30 anos? | C26: =FV($D$17,$A26*12,$D$15*-1) -> 864433.93 | D26: =C26*rendimento_carteira -> 5186.6036
B28: Perfil | C28: Moderado
B29: VALOR A SER INVESTIDO POR MÊS | C29: =aporte -> 200
B31: TIPO DE FII | C31: Percentual sugerido | D31: Valores
B32: PAPEL | C32: =VLOOKUP($C$28&"-"&B32,Planilha2!$A:$D,4,FALSE) -> 0.32 | D32: =C32*$C$29 -> 64
B33: TIJOLO | C33: =VLOOKUP($C$28&"-"&B33,Planilha2!$A:$D,4,FALSE) -> 0.35 | D33: =C33*$C$29 -> 70
B34: HÍBRIDOS | C34: =VLOOKUP($C$28&"-"&B34,Planilha2!$A:$D,4,FALSE) -> 0.08 | D34: =C34*$C$29 -> 16
B35: FOF's | C35: =VLOOKUP($C$28&"-"&B35,Planilha2!$A:$D,4,FALSE) -> 0.05 | D35: =C35*$C$29 -> 10
B36: DESENVOLVIMENTO | C36: =VLOOKUP($C$28&"-"&B36,Planilha2!$A:$D,4,FALSE) -> 0.1 | D36: =C36*$C$29 -> 20
B37: HOTELARIAS | C37: =VLOOKUP($C$28&"-"&B37,Planilha2!$A:$D,4,FALSE) -> 0.1 | D37: =C37*$C$29 -> 20
D38: =SUM(D32:D37) -> 200

Sheet Planilha2
A1: CHAVE | B1: PERFIL | C1: TIPO DE FII | D1: %
A2: Conservador-PAPEL | B2: Conservador | C2: PAPEL | D2: 0.3
A3: Conservador-TIJOLO | B3: Conservador | C3: TIJOLO | D3: 0.5
A4: Conservador-HÍBRIDOS | B4: Conservador | C4: HÍBRIDOS | D4: 0.1 | G4: Moderado-TIJOLO | H4: =VLOOKUP(G4,$A:$D,4,FALSE) -> 0.35
A5: Conservador-FOF's | B5: Conservador | C5: FOF's | D5: 0.1
A6: Conservador-DESENVOLVIMENTO | B6: Conservador | C6: DESENVOLVIMENTO | D6: 0
A7: Conservador-HOTELARIAS | B7: Conservador | C7: HOTELARIAS | D7: 0
A8: Moderado-PAPEL | B8: Moderado | C8: PAPEL | D8: 0.32
A9: Moderado-TIJOLO | B9: Moderado | C9: TIJOLO | D9: 0.35
A10: Moderado-HÍBRIDOS | B10: Moderado | C10: HÍBRIDOS | D10: 0.08
A11: Moderado-FOF's | B11: Moderado | C11: FOF's | D11: 0.05
A12: Moderado-DESENVOLVIMENTO | B12: Moderado | C12: DESENVOLVIMENTO | D12: 0.1
A13: Moderado-HOTELARIAS | B13: Moderado | C13: HOTELARIAS | D13: 0.1
A14: Agressivo-PAPEL | B14: Agressivo | C14: PAPEL | D14: 0.5
A15: Agressivo-TIJOLO | B15: Agressivo | C15: TIJOLO | D15: 0.1
A16: Agressivo-HÍBRIDOS | B16: Agressivo | C16: HÍBRIDOS | D16: 0.05
... A19: Agressivo-HOTELARIAS | B19: Agressivo | C19: HOTELARIAS | D19: 0.1
